cpskin/__init__.py
cpskin/menu/__init__.py
cpskin/menu/cache.py
cpskin/menu/configure.zcml
cpskin/menu/interfaces.py
cpskin/menu/meta.zcml
cpskin/menu/overrides.zcml
cpskin/menu/setuphandlers.py
cpskin/menu/subscribers.py
cpskin/menu/subscribers.zcml
cpskin/menu/testing.py
cpskin/menu/testing.zcml
cpskin/menu/upgrades.py
cpskin/menu/vocabulary.py
cpskin/menu/browser/__init__.py
cpskin/menu/browser/configure.zcml
cpskin/menu/browser/directaccessview.py
cpskin/menu/browser/menu.pt
cpskin/menu/browser/menu.py
cpskin/menu/browser/navigationview.py
cpskin/menu/browser/resources/cpskin_menu.js
cpskin/menu/browser/resources/cpskin_not_persistent.js
cpskin/menu/browser/resources/detectizr.min.js
cpskin/menu/browser/resources/detectizr.min.map
cpskin/menu/browser/resources/menu.css
cpskin/menu/browser/resources/menu_mobile.css
cpskin/menu/browser/resources/modernizr.min.js
cpskin/menu/browser/resources/search.png
cpskin/menu/browser/resources/superfish.js
cpskin/menu/browser/resources/superfish_init.js
cpskin/menu/overrides/plone.app.layout.viewlets.sections.pt
cpskin/menu/profiles/default/actions.xml
cpskin/menu/profiles/default/browserlayer.xml
cpskin/menu/profiles/default/cpskin.menu-default.txt
cpskin/menu/profiles/default/cssregistry.xml
cpskin/menu/profiles/default/import_steps.xml
cpskin/menu/profiles/default/jsregistry.xml
cpskin/menu/profiles/default/metadata.xml
cpskin/menu/profiles/default/viewlets.xml
cpskin/menu/profiles/testing/metadata.xml
cpskin/menu/profiles/testing/theme.xml
cpskin/menu/profiles/testing-load-page/cpskin.menu.content.txt
cpskin/menu/profiles/testing-load-page/metadata.xml
cpskin/menu/profiles/testing-load-page/registry.xml
cpskin/menu/profiles/testing-no-persistence/cpskin.menu.content.txt
cpskin/menu/profiles/testing-no-persistence/metadata.xml
cpskin/menu/profiles/testing-no-persistence/registry.xml
cpskin/menu/profiles/testing-persistence/cpskin.menu.content.txt
cpskin.menu-0.7.2.dist-info/DESCRIPTION.rst
cpskin.menu-0.7.2.dist-info/METADATA
cpskin.menu-0.7.2.dist-info/RECORD
cpskin.menu-0.7.2.dist-info/WHEEL
cpskin.menu-0.7.2.dist-info/metadata.json
cpskin.menu-0.7.2.dist-info/top_level.txt
