Metadata-Version: 2.0
Name: cpskin.menu
Version: 0.7.2
Summary: Menu package for cpskin
Home-page: https://github.com/imio/cpskin.menu
Author: IMIO
Author-email: support@imio.be
License: gpl
Platform: UNKNOWN
Classifier: Environment :: Web Environment
Classifier: Programming Language :: Python
Classifier: Programming Language :: Python :: 2.7
Classifier: Framework :: Plone
Classifier: Framework :: Plone :: 4.2
Classifier: Framework :: Plone :: 4.3
Provides-Extra: test
Requires-Dist: setuptools
Requires-Dist: plone.api
Requires-Dist: Plone
Requires-Dist: cpskin.core
Requires-Dist: cpskin.locales
Requires-Dist: cpskin.theme
Requires-Dist: collective.superfish
Requires-Dist: z3c.jbot
Requires-Dist: affinitic.caching (>=0.7.1)
Provides-Extra: test
Requires-Dist: Mock; extra == 'test'
Requires-Dist: plone.api; extra == 'test'
Requires-Dist: plone.app.multilingual; extra == 'test'
Requires-Dist: plone.app.robotframework[debug]; extra == 'test'
Requires-Dist: plone.app.testing; extra == 'test'
Requires-Dist: z3c.unconfigure; extra == 'test'
Requires-Dist: cpskin.menu; extra == 'test'
Requires-Dist: cpskin.workflow; extra == 'test'
Requires-Dist: sc.social.like; extra == 'test'
